[
    {
        "friendUsername": "Robert Zenden",
        "friendUserImageUrl": "user1",
        "friendLastMessage": "How are you?",
        "friendUserId": "hgjgjgjjhgjhgghg"
    },
    {
        "friendUsername": "John Smith",
        "friendUserImageUrl": "user2",
        "friendLastMessage": "Where are you?",
        "friendUserId": "mdbnfjhasfkhk"
    },
    {
        "friendUsername": "Michel Night",
        "friendUserImageUrl": "user3",
        "friendLastMessage": "Who are you?",
        "friendUserId": "nfjhagfhdsfhjadf"
    },
    {
        "friendUsername": "Alexander Jenkins",
        "friendUserImageUrl": "user4",
        "friendLastMessage": "How old are you?",
        "friendUserId": "nzbncnxzbchaJD"
    },
    {
        "friendUsername": "Veronica White",
        "friendUserImageUrl": "user5",
        "friendLastMessage": "Where are we?",
        "friendUserId": "XBVSDVFAGFVDAGHJ"
    }
]

